SkitterSchema/__init__.py
SkitterSchema/tweepy2schema.py
SkitterSchema/twitter_schema.py
SkitterSchema/util.py
SkitterSchema-0.0.7.dist-info/DESCRIPTION.rst
SkitterSchema-0.0.7.dist-info/METADATA
SkitterSchema-0.0.7.dist-info/RECORD
SkitterSchema-0.0.7.dist-info/WHEEL
SkitterSchema-0.0.7.dist-info/metadata.json
SkitterSchema-0.0.7.dist-info/top_level.txt
