Metadata-Version: 2.0
Name: SkitterSchema
Version: 0.0.7
Summary: OSN schema for online social networks.
Home-page: https://github.com/manoelhortaribeiro/SkitterSchema
Author: Manoel Horta Ribeiro
Author-email: manoelhortaribeiro@gmail.com
License: MIT
Download-URL: https://github.com/manoelhortaribeiro/SkitterSchema
Keywords: ORM schema online social network
Platform: UNKNOWN
Requires-Dist: sqlalchemy
